MANIFEST.in
README.rst
setup.py
Py_Infinote.egg-info/PKG-INFO
Py_Infinote.egg-info/SOURCES.txt
Py_Infinote.egg-info/dependency_links.txt
Py_Infinote.egg-info/not-zip-safe
Py_Infinote.egg-info/top_level.txt
infinote/__init__.py
infinote/document.py
infinote/protocol.py
infinote/tests.py