Metadata-Version: 1.1
Name: Py-Infinote
Version: 0.93
Summary: Py-Infinote is a Python implementation of the infinote     operation transformation protocol. It's a direct port of JInfinote
Home-page: https://github.com/phrearch/py-infinote
Author: Jeroen van Veen
Author-email: j.veenvan@gmail.com
License: BSD
Keywords: infinote,text,editing,collaborative,ot,adopted
Platform: UNKNOWN
Classifier: Development Status :: 4 - Beta
Classifier: Environment :: Web Environment
Classifier: Intended Audience :: Information Technology
Classifier: Natural Language :: English
Classifier: Programming Language :: Python
Classifier: Topic :: Software Development
Classifier: Operating System :: OS Independent
